<list>
  <ProcessDefinition>
    <processDefinitionPK>
      <companyId>1</companyId>
      <processId>Solicitação de Peças</processId>
    </processDefinitionPK>
    <processDescription>Solicitação de Peças</processDescription>
    <instruction>Solicita08 - Solicita Peças da Matriz para Filial</instruction>
    <active>true</active>
    <publicProcess>true</publicProcess>
    <volumeId>Default</volumeId>
    <categoryId>PCP</categoryId>
    <managerEngineAllocationId>Grupo</managerEngineAllocationId>
    <managerEngineAllocationConfiguration>&lt;AssignmentController&gt;&lt;Group&gt;GestorSolicitaoPecas&lt;/Group&gt;&lt;/AssignmentController&gt;</managerEngineAllocationConfiguration>
    <snapshotFrequency>0</snapshotFrequency>
    <baseDay>0</baseDay>
    <baseMonth>0</baseMonth>
    <periodId>Default</periodId>
    <uniqueCardVersion>false</uniqueCardVersion>
    <keyWord></keyWord>
    <complementsLevel>1</complementsLevel>
    <notifyRequisitionerComplements>true</notifyRequisitionerComplements>
    <notifyManagerComplements>false</notifyManagerComplements>
    <deadlineTime>0</deadlineTime>
    <warningDeadlineTime>0</warningDeadlineTime>
    <notifyAuthorityComplements>true</notifyAuthorityComplements>
  </ProcessDefinition>
  <ProcessDefinitionVersion>
    <processDefinitionVersionPK>
      <companyId>1</companyId>
      <processId>Solicitação de Peças</processId>
      <version>6</version>
    </processDefinitionVersionPK>
    <versionDescription></versionDescription>
    <formId>5606</formId>
    <editionMode>true</editionMode>
    <updateAttachmentsVersion>false</updateAttachmentsVersion>
    <controlsAttachmentsSecurity>false</controlsAttachmentsSecurity>
    <active>true</active>
    <blockedVersion>false</blockedVersion>
    <counterSign>false</counterSign>
    <openInstances>0</openInstances>
    <bpmnVersion>2</bpmnVersion>
    <processStates/>
    <favorito>false</favorito>
    <inheritFormSecurity>false</inheritFormSecurity>
    <mobileReady>false</mobileReady>
  </ProcessDefinitionVersion>
  <list>
    <ProcessState>
      <processStatePK>
        <companyId>1</companyId>
        <processId>Solicitação de Peças</processId>
        <version>1</version>
        <sequence>4</sequence>
      </processStatePK>
      <stateName>Início</stateName>
      <stateDescription>Início</stateDescription>
      <instruction>SolicitaPecasFilial</instruction>
      <deadlineTime>0</deadlineTime>
      <joint>false</joint>
      <agreementPercentage>0</agreementPercentage>
      <engineAllocationId>Grupo</engineAllocationId>
      <engineAllocationConfiguration>&lt;AssignmentController&gt;&lt;Group&gt;SolicitaPecasFilial&lt;/Group&gt;&lt;/AssignmentController&gt;</engineAllocationConfiguration>
      <selectColleague>1</selectColleague>
      <initialState>true</initialState>
      <notifyAuthorityDelay>true</notifyAuthorityDelay>
      <notifyRequisitionerDelay>false</notifyRequisitionerDelay>
      <allowanceAuthorityTime>3600</allowanceAuthorityTime>
      <frequenceAuthorityTime>3600</frequenceAuthorityTime>
      <allowanceRequisitionerTime>0</allowanceRequisitionerTime>
      <frequenceRequisitionerTime>0</frequenceRequisitionerTime>
      <transferAttachments>false</transferAttachments>
      <subProcessId></subProcessId>
      <formFolder>0</formFolder>
      <notifyAuthorityFollowUp>false</notifyAuthorityFollowUp>
      <notifyRequisitionerFollowUp>false</notifyRequisitionerFollowUp>
      <automatic>false</automatic>
      <positionX>150</positionX>
      <positionY>41</positionY>
      <forecastedEffortType>0</forecastedEffortType>
      <forecastedEffort>0</forecastedEffort>
      <notifyManagerFollowUp>false</notifyManagerFollowUp>
      <notifyManagerDelay>false</notifyManagerDelay>
      <allowanceManagerTime>0</allowanceManagerTime>
      <frequenceManagerTime>0</frequenceManagerTime>
      <inhibitTransfer>false</inhibitTransfer>
      <periodId></periodId>
      <stateType>0</stateType>
      <bpmnType>10</bpmnType>
      <signalId>0</signalId>
      <counterSign>false</counterSign>
      <openInstances>0</openInstances>
      <noticeExpirationAuthorityTime>0</noticeExpirationAuthorityTime>
      <noticeExpirationRequisitionerTime>0</noticeExpirationRequisitionerTime>
      <noticeExpirationManagerTime>0</noticeExpirationManagerTime>
      <destinationStates/>
      <digitalSignature>false</digitalSignature>
    </ProcessState>
    <ProcessState>
      <processStatePK>
        <companyId>1</companyId>
        <processId>Solicitação de Peças</processId>
        <version>1</version>
        <sequence>5</sequence>
      </processStatePK>
      <stateName>ANALISA_SOLICITACAO</stateName>
      <stateDescription>ANALISA_SOLICITACAO</stateDescription>
      <instruction>GestorSolicitacaoPecas</instruction>
      <deadlineTime>0</deadlineTime>
      <deadlineFieldName></deadlineFieldName>
      <joint>false</joint>
      <agreementPercentage>0</agreementPercentage>
      <engineAllocationId>Pool Grupo</engineAllocationId>
      <engineAllocationConfiguration>&lt;AssignmentController&gt;&lt;Group&gt;GestorSolicitaoPecas&lt;/Group&gt;&lt;/AssignmentController&gt;</engineAllocationConfiguration>
      <selectColleague>1</selectColleague>
      <initialState>false</initialState>
      <notifyAuthorityDelay>true</notifyAuthorityDelay>
      <notifyRequisitionerDelay>false</notifyRequisitionerDelay>
      <allowanceAuthorityTime>3600</allowanceAuthorityTime>
      <frequenceAuthorityTime>3600</frequenceAuthorityTime>
      <allowanceRequisitionerTime>0</allowanceRequisitionerTime>
      <frequenceRequisitionerTime>0</frequenceRequisitionerTime>
      <transferAttachments>false</transferAttachments>
      <subProcessId></subProcessId>
      <formFolder>0</formFolder>
      <notifyAuthorityFollowUp>true</notifyAuthorityFollowUp>
      <notifyRequisitionerFollowUp>false</notifyRequisitionerFollowUp>
      <automatic>false</automatic>
      <positionX>240</positionX>
      <positionY>120</positionY>
      <forecastedEffortType>0</forecastedEffortType>
      <forecastedEffort>0</forecastedEffort>
      <notifyManagerFollowUp>false</notifyManagerFollowUp>
      <notifyManagerDelay>false</notifyManagerDelay>
      <allowanceManagerTime>0</allowanceManagerTime>
      <frequenceManagerTime>0</frequenceManagerTime>
      <inhibitTransfer>false</inhibitTransfer>
      <periodId></periodId>
      <stateType>0</stateType>
      <bpmnType>80</bpmnType>
      <signalId>0</signalId>
      <counterSign>false</counterSign>
      <openInstances>0</openInstances>
      <noticeExpirationAuthorityTime>0</noticeExpirationAuthorityTime>
      <noticeExpirationRequisitionerTime>0</noticeExpirationRequisitionerTime>
      <noticeExpirationManagerTime>0</noticeExpirationManagerTime>
      <destinationStates/>
      <digitalSignature>false</digitalSignature>
      <executionType>0</executionType>
    </ProcessState>
    <ProcessState>
      <processStatePK>
        <companyId>1</companyId>
        <processId>Solicitação de Peças</processId>
        <version>1</version>
        <sequence>12</sequence>
      </processStatePK>
      <stateName>SEPARACAO_ALMOX</stateName>
      <stateDescription>SEPARACAO_ALMOX</stateDescription>
      <instruction>SeparacaoPecasAlmox</instruction>
      <deadlineTime>0</deadlineTime>
      <deadlineFieldName></deadlineFieldName>
      <joint>false</joint>
      <agreementPercentage>0</agreementPercentage>
      <engineAllocationId>Pool Grupo</engineAllocationId>
      <engineAllocationConfiguration>&lt;AssignmentController&gt;&lt;Group&gt;SeparacaoPecasAlmox&lt;/Group&gt;&lt;/AssignmentController&gt;</engineAllocationConfiguration>
      <selectColleague>1</selectColleague>
      <initialState>false</initialState>
      <notifyAuthorityDelay>true</notifyAuthorityDelay>
      <notifyRequisitionerDelay>false</notifyRequisitionerDelay>
      <allowanceAuthorityTime>3600</allowanceAuthorityTime>
      <frequenceAuthorityTime>3600</frequenceAuthorityTime>
      <allowanceRequisitionerTime>0</allowanceRequisitionerTime>
      <frequenceRequisitionerTime>0</frequenceRequisitionerTime>
      <transferAttachments>false</transferAttachments>
      <subProcessId></subProcessId>
      <formFolder>0</formFolder>
      <notifyAuthorityFollowUp>true</notifyAuthorityFollowUp>
      <notifyRequisitionerFollowUp>false</notifyRequisitionerFollowUp>
      <automatic>false</automatic>
      <positionX>530</positionX>
      <positionY>224</positionY>
      <forecastedEffortType>0</forecastedEffortType>
      <forecastedEffort>0</forecastedEffort>
      <notifyManagerFollowUp>false</notifyManagerFollowUp>
      <notifyManagerDelay>false</notifyManagerDelay>
      <allowanceManagerTime>0</allowanceManagerTime>
      <frequenceManagerTime>0</frequenceManagerTime>
      <inhibitTransfer>false</inhibitTransfer>
      <periodId></periodId>
      <stateType>0</stateType>
      <bpmnType>80</bpmnType>
      <signalId>0</signalId>
      <counterSign>false</counterSign>
      <openInstances>0</openInstances>
      <noticeExpirationAuthorityTime>0</noticeExpirationAuthorityTime>
      <noticeExpirationRequisitionerTime>0</noticeExpirationRequisitionerTime>
      <noticeExpirationManagerTime>0</noticeExpirationManagerTime>
      <destinationStates/>
      <digitalSignature>false</digitalSignature>
      <executionType>0</executionType>
    </ProcessState>
    <ProcessState>
      <processStatePK>
        <companyId>1</companyId>
        <processId>Solicitação de Peças</processId>
        <version>1</version>
        <sequence>8</sequence>
      </processStatePK>
      <stateName>APROVA_SOLICITACAO?</stateName>
      <stateDescription>APROVA_SOLICITACAO?</stateDescription>
      <joint>false</joint>
      <initialState>false</initialState>
      <transferAttachments>false</transferAttachments>
      <subProcessId></subProcessId>
      <formFolder>0</formFolder>
      <automatic>true</automatic>
      <positionX>460</positionX>
      <positionY>104</positionY>
      <inhibitTransfer>false</inhibitTransfer>
      <stateType>1</stateType>
      <bpmnType>120</bpmnType>
      <signalId>0</signalId>
      <openInstances>0</openInstances>
      <destinationStates/>
      <digitalSignature>false</digitalSignature>
    </ProcessState>
    <ProcessState>
      <processStatePK>
        <companyId>1</companyId>
        <processId>Solicitação de Peças</processId>
        <version>1</version>
        <sequence>14</sequence>
      </processStatePK>
      <stateName>Fim</stateName>
      <stateDescription>Fim</stateDescription>
      <instruction>Atividade final do processo</instruction>
      <deadlineTime>0</deadlineTime>
      <joint>false</joint>
      <agreementPercentage>0</agreementPercentage>
      <engineAllocationId></engineAllocationId>
      <engineAllocationConfiguration></engineAllocationConfiguration>
      <selectColleague>0</selectColleague>
      <initialState>false</initialState>
      <notifyAuthorityDelay>true</notifyAuthorityDelay>
      <notifyRequisitionerDelay>false</notifyRequisitionerDelay>
      <allowanceAuthorityTime>0</allowanceAuthorityTime>
      <frequenceAuthorityTime>1</frequenceAuthorityTime>
      <allowanceRequisitionerTime>0</allowanceRequisitionerTime>
      <frequenceRequisitionerTime>0</frequenceRequisitionerTime>
      <transferAttachments>false</transferAttachments>
      <subProcessId></subProcessId>
      <formFolder>0</formFolder>
      <notifyAuthorityFollowUp>false</notifyAuthorityFollowUp>
      <notifyRequisitionerFollowUp>false</notifyRequisitionerFollowUp>
      <automatic>false</automatic>
      <positionX>720</positionX>
      <positionY>234</positionY>
      <forecastedEffortType>0</forecastedEffortType>
      <forecastedEffort>0</forecastedEffort>
      <notifyManagerFollowUp>false</notifyManagerFollowUp>
      <notifyManagerDelay>false</notifyManagerDelay>
      <allowanceManagerTime>0</allowanceManagerTime>
      <frequenceManagerTime>0</frequenceManagerTime>
      <inhibitTransfer>false</inhibitTransfer>
      <periodId></periodId>
      <stateType>6</stateType>
      <bpmnType>60</bpmnType>
      <signalId>0</signalId>
      <counterSign>false</counterSign>
      <openInstances>0</openInstances>
      <destinationStates/>
      <digitalSignature>false</digitalSignature>
    </ProcessState>
  </list>
  <list>
    <ConditionProcessState>
      <conditionProcessStatePK>
        <companyId>1</companyId>
        <processId>Solicitação de Peças</processId>
        <expressionOrder>1</expressionOrder>
        <version>6</version>
        <sequence>8</sequence>
      </conditionProcessStatePK>
      <condition>&#xd;
hAPI.getCardValue(&quot;solAprovacao&quot;) == &quot;reprovado&quot;</condition>
      <destinationSequenceId>14</destinationSequenceId>
      <conditionType>0</conditionType>
    </ConditionProcessState>
    <ConditionProcessState>
      <conditionProcessStatePK>
        <companyId>1</companyId>
        <processId>Solicitação de Peças</processId>
        <expressionOrder>2</expressionOrder>
        <version>6</version>
        <sequence>8</sequence>
      </conditionProcessStatePK>
      <condition>&#xd;
hAPI.getCardValue(&quot;solAprovacao&quot;) == &quot;aprovado&quot;</condition>
      <destinationSequenceId>12</destinationSequenceId>
      <engineAllocationConfiguration>&lt;AssignmentController&gt;&lt;Group&gt;AnalisaRelatorio&lt;/Group&gt;&lt;/AssignmentController&gt;</engineAllocationConfiguration>
      <conditionType>0</conditionType>
    </ConditionProcessState>
  </list>
  <list>
    <ProcessLink>
      <processLinkPK>
        <companyId>1</companyId>
        <processId>Solicitação de Peças</processId>
        <version>1</version>
        <linkSequence>6</linkSequence>
      </processLinkPK>
      <actionLabel></actionLabel>
      <returnPermited>false</returnPermited>
      <initialStateSequence>4</initialStateSequence>
      <finalStateSequence>5</finalStateSequence>
      <returnLabel></returnLabel>
      <name></name>
      <automaticLink>false</automaticLink>
      <defaultLink>false</defaultLink>
      <type>0</type>
    </ProcessLink>
    <ProcessLink>
      <processLinkPK>
        <companyId>1</companyId>
        <processId>Solicitação de Peças</processId>
        <version>1</version>
        <linkSequence>9</linkSequence>
      </processLinkPK>
      <actionLabel></actionLabel>
      <returnPermited>false</returnPermited>
      <initialStateSequence>5</initialStateSequence>
      <finalStateSequence>8</finalStateSequence>
      <returnLabel></returnLabel>
      <name></name>
      <automaticLink>false</automaticLink>
      <defaultLink>false</defaultLink>
      <type>0</type>
    </ProcessLink>
    <ProcessLink>
      <processLinkPK>
        <companyId>1</companyId>
        <processId>Solicitação de Peças</processId>
        <version>1</version>
        <linkSequence>13</linkSequence>
      </processLinkPK>
      <actionLabel></actionLabel>
      <returnPermited>false</returnPermited>
      <initialStateSequence>8</initialStateSequence>
      <finalStateSequence>12</finalStateSequence>
      <returnLabel></returnLabel>
      <name></name>
      <automaticLink>false</automaticLink>
      <defaultLink>false</defaultLink>
      <type>0</type>
    </ProcessLink>
    <ProcessLink>
      <processLinkPK>
        <companyId>1</companyId>
        <processId>Solicitação de Peças</processId>
        <version>1</version>
        <linkSequence>15</linkSequence>
      </processLinkPK>
      <actionLabel></actionLabel>
      <returnPermited>false</returnPermited>
      <initialStateSequence>12</initialStateSequence>
      <finalStateSequence>14</finalStateSequence>
      <returnLabel></returnLabel>
      <name></name>
      <automaticLink>false</automaticLink>
      <defaultLink>false</defaultLink>
      <type>0</type>
    </ProcessLink>
    <ProcessLink>
      <processLinkPK>
        <companyId>1</companyId>
        <processId>Solicitação de Peças</processId>
        <version>1</version>
        <linkSequence>16</linkSequence>
      </processLinkPK>
      <actionLabel></actionLabel>
      <returnPermited>false</returnPermited>
      <initialStateSequence>8</initialStateSequence>
      <finalStateSequence>14</finalStateSequence>
      <returnLabel></returnLabel>
      <name></name>
      <automaticLink>false</automaticLink>
      <defaultLink>false</defaultLink>
      <type>0</type>
    </ProcessLink>
  </list>
  <list/>
  <list>
    <WorkflowProcessEvent>
      <workflowProcessEventPK>
        <companyId>1</companyId>
        <eventId>ENG_LITERALS</eventId>
        <processId>Solicitação de Peças</processId>
        <version>1</version>
      </workflowProcessEventPK>
      <eventDescription>#Wed Oct 05 14:30:52 BRT 2022&#xd;
process.category=&#xd;
process.description=Solicita\u00E7\u00E3oDePe\u00E7as&#xd;
process.instructions=&#xd;
</eventDescription>
    </WorkflowProcessEvent>
    <WorkflowProcessEvent>
      <workflowProcessEventPK>
        <companyId>1</companyId>
        <eventId>ESP_LITERALS</eventId>
        <processId>Solicitação de Peças</processId>
        <version>1</version>
      </workflowProcessEventPK>
      <eventDescription>#Wed Oct 05 14:30:52 BRT 2022&#xd;
process.category=&#xd;
process.description=Solicita\u00E7\u00E3oDePe\u00E7as&#xd;
process.instructions=&#xd;
</eventDescription>
    </WorkflowProcessEvent>
    <WorkflowProcessEvent>
      <workflowProcessEventPK>
        <companyId>1</companyId>
        <eventId>POR_LITERALS</eventId>
        <processId>Solicitação de Peças</processId>
        <version>1</version>
      </workflowProcessEventPK>
      <eventDescription>#Wed Oct 05 14:30:52 BRT 2022&#xd;
process.category=&#xd;
process.description=Solicita\u00E7\u00E3oDePe\u00E7as&#xd;
process.instructions=&#xd;
</eventDescription>
    </WorkflowProcessEvent>
  </list>
  <list/>
  <list>
    <SwimLane>
      <color>FFFFFF</color>
      <height>290</height>
      <width>831</width>
      <positionX>10</positionX>
      <positionY>10</positionY>
      <stateName>Pool</stateName>
      <type>1</type>
      <parentSequence>0</parentSequence>
      <swimLanePK>
        <companyId>1</companyId>
        <processId>Solicitação de Peças</processId>
        <version>1</version>
        <sequence>1</sequence>
      </swimLanePK>
    </SwimLane>
    <SwimLane>
      <color>9F9F9F</color>
      <height>96</height>
      <width>801</width>
      <positionX>40</positionX>
      <positionY>10</positionY>
      <stateName>Comercial</stateName>
      <type>2</type>
      <parentSequence>1</parentSequence>
      <swimLanePK>
        <companyId>1</companyId>
        <processId>Solicitação de Peças</processId>
        <version>1</version>
        <sequence>2</sequence>
      </swimLanePK>
    </SwimLane>
    <SwimLane>
      <color>C0C0C0</color>
      <height>98</height>
      <width>801</width>
      <positionX>40</positionX>
      <positionY>202</positionY>
      <stateName>PCP</stateName>
      <type>2</type>
      <parentSequence>1</parentSequence>
      <swimLanePK>
        <companyId>1</companyId>
        <processId>Solicitação de Peças</processId>
        <version>1</version>
        <sequence>3</sequence>
      </swimLanePK>
    </SwimLane>
    <SwimLane>
      <color>82b0b7</color>
      <height>96</height>
      <width>801</width>
      <positionX>40</positionX>
      <positionY>106</positionY>
      <stateName>Amox</stateName>
      <type>2</type>
      <parentSequence>1</parentSequence>
      <swimLanePK>
        <companyId>1</companyId>
        <processId>Solicitação de Peças</processId>
        <version>1</version>
        <sequence>4</sequence>
      </swimLanePK>
    </SwimLane>
  </list>
  <list/>
  <list/>
  <list>
    <ProcessLinkBend>
      <processLinkBendPK>
        <companyId>1</companyId>
        <processId>Solicitação de Peças</processId>
        <version>6</version>
        <linkSequence>6</linkSequence>
        <bendSequence>1</bendSequence>
      </processLinkBendPK>
      <positionX>167</positionX>
      <positionY>155</positionY>
    </ProcessLinkBend>
    <ProcessLinkBend>
      <processLinkBendPK>
        <companyId>1</companyId>
        <processId>Solicitação de Peças</processId>
        <version>6</version>
        <linkSequence>16</linkSequence>
        <bendSequence>1</bendSequence>
      </processLinkBendPK>
      <positionX>737</positionX>
      <positionY>161</positionY>
    </ProcessLinkBend>
  </list>
  <list/>
  <list/>
  <list/>
  <list/>
  <list/>
  <list/>
  <list/>
  <list/>
</list>